paysdk/__init__.py
paysdk/api.py
paysdk/base.py
paysdk/config.py
paysdk-2.1.0.dist-info/METADATA
paysdk-2.1.0.dist-info/RECORD
paysdk-2.1.0.dist-info/WHEEL
paysdk-2.1.0.dist-info/top_level.txt
