Metadata-Version: 2.1
Name: paysdk
Version: 2.1.0
Summary: paysdk, make payment simpler
Home-page: https://jasonhzy.github.io
Author: jasonhzy
Author-email: jasonhzy@yeah.net
License: MIT License
Download-URL: https://github.com/jasonhzy/paysdk-python
Keywords: paysdk,python
Platform: 2.6
Platform: 2.7
Platform: 3.3
Platform: 3.4
Platform: 3.5
Platform: 3.6
Classifier: Intended Audience :: Developers
Classifier: License :: OSI Approved :: MIT License
Classifier: Natural Language :: English
Classifier: Operating System :: Microsoft :: Windows
Classifier: Operating System :: MacOS
Classifier: Operating System :: Unix
Classifier: Programming Language :: Python
Classifier: Programming Language :: Python :: 2.6
Classifier: Programming Language :: Python :: 2.7
Classifier: Programming Language :: Python :: 3.3
Classifier: Programming Language :: Python :: 3.4
Classifier: Programming Language :: Python :: 3.5
Classifier: Programming Language :: Python :: 3.6
Classifier: Topic :: Software Development :: Libraries
Requires-Dist: Flask
